njaXt/__init__.py
njaXt/fuzzer.py
njaXt/fuzzer_ui.py
njaXt/main.py
njaXt/njaxt.py
njaXt/njaxt_ui.py
njaXt/payloads.py
njaXt/payloads_ui.py
njaXt-0.1.dist-info/DESCRIPTION.rst
njaXt-0.1.dist-info/METADATA
njaXt-0.1.dist-info/RECORD
njaXt-0.1.dist-info/WHEEL
njaXt-0.1.dist-info/entry_points.txt
njaXt-0.1.dist-info/metadata.json
njaXt-0.1.dist-info/top_level.txt
